zipdir/__init__.py
zipdir-0.1.2.dist-info/DESCRIPTION.rst
zipdir-0.1.2.dist-info/METADATA
zipdir-0.1.2.dist-info/RECORD
zipdir-0.1.2.dist-info/WHEEL
zipdir-0.1.2.dist-info/metadata.json
zipdir-0.1.2.dist-info/top_level.txt
