Metadata-Version: 2.0
Name: zipdir
Version: 0.1.2
Summary: zip entire directories recursively
Home-page: https://github.com/haarcuba/zipdir
Author: Yoav Kleinberger
Author-email: haarcuba@gmail.com
License: UNKNOWN
Keywords: zip
Platform: UNKNOWN
Classifier: Programming Language :: Python
Provides-Extra: testing
